{
  "schema_version": 1,
  "season": "KCC2026",
  "generated_at": "2026-06-28T12:22:14+08:00",
  "build_id": "20260628T122214+0800",
  "data": {
    "code": 200,
    "data": [
      {
        "created_at": "2026-05-28 23:55:11",
        "damage_output": 79,
        "damage_output_overall_rank": 108.0,
        "damage_output_position_rank": 19.0,
        "data_completeness": 100,
        "durability": 25,
        "durability_overall_rank": 121.0,
        "durability_position_rank": 25.0,
        "early_game": 65,
        "early_game_overall_rank": 116.0,
        "early_game_position_rank": 22.0,
        "economy": 98,
        "economy_overall_rank": 17.0,
        "economy_position_rank": 2.0,
        "initiation": 100,
        "initiation_overall_rank": 1.0,
        "initiation_position_rank": 1.0,
        "invasion_ability": 26,
        "invasion_ability_overall_rank": 73.0,
        "invasion_ability_position_rank": 13.0,
        "last_updated": "2026-05-29 02:16:58",
        "late_game": 56,
        "late_game_overall_rank": 89.0,
        "late_game_position_rank": 20.0,
        "map_control": 72,
        "map_control_overall_rank": 99.0,
        "map_control_position_rank": 18.0,
        "mid_game": 75,
        "mid_game_overall_rank": 91.0,
        "mid_game_position_rank": 22.0,
        "overall_rank": 95.0,
        "overall_rank_change": 0.0,
        "overall_rank_trend": "SAME",
        "overall_rating": 69.23,
        "player_name": "KSG.无言",
        "player_position": "对抗路",
        "position_rank": 20.0,
        "position_rank_change": 0.0,
        "position_rank_trend": "SAME",
        "previous_overall_rank": 95.0,
        "previous_position_rank": 20.0,
        "season": "KCC2026",
        "support_ability": 57,
        "support_ability_overall_rank": 131.0,
        "support_ability_position_rank": 27.0,
        "tankiness": 89,
        "tankiness_overall_rank": 53.0,
        "tankiness_position_rank": 18.0,
        "team_name": "KSG",
        "teamfight": 61,
        "teamfight_overall_rank": 106.0,
        "teamfight_position_rank": 23.0,
        "total_matches": 4.0
      }
    ],
    "player_name": null,
    "position": "对抗路",
    "position_averages": {
      "中路": {
        "damage_output": 83,
        "durability": 48,
        "early_game": 72,
        "economy": 78,
        "initiation": 69,
        "invasion_ability": 27,
        "late_game": 61,
        "map_control": 74,
        "mid_game": 71,
        "overall_rating": 68.03,
        "support_ability": 79,
        "tankiness": 76,
        "teamfight": 64
      },
      "发育路": {
        "damage_output": 84,
        "durability": 44,
        "early_game": 73,
        "economy": 81,
        "initiation": 68,
        "invasion_ability": 20,
        "late_game": 62,
        "map_control": 73,
        "mid_game": 75,
        "overall_rating": 69.36,
        "support_ability": 81,
        "tankiness": 83,
        "teamfight": 66
      },
      "对抗路": {
        "damage_output": 78,
        "durability": 40,
        "early_game": 66,
        "economy": 77,
        "initiation": 68,
        "invasion_ability": 22,
        "late_game": 62,
        "map_control": 70,
        "mid_game": 75,
        "overall_rating": 67.91,
        "support_ability": 72,
        "tankiness": 90,
        "teamfight": 64
      },
      "打野": {
        "damage_output": 88,
        "durability": 49,
        "early_game": 73,
        "economy": 80,
        "initiation": 69,
        "invasion_ability": 26,
        "late_game": 63,
        "map_control": 75,
        "mid_game": 75,
        "overall_rating": 68.81,
        "support_ability": 78,
        "tankiness": 76,
        "teamfight": 68
      },
      "游走": {
        "damage_output": 83,
        "durability": 38,
        "early_game": 74,
        "economy": 80,
        "initiation": 52,
        "invasion_ability": 18,
        "late_game": 62,
        "map_control": 74,
        "mid_game": 77,
        "overall_rating": 67.93,
        "support_ability": 73,
        "tankiness": 90,
        "teamfight": 65
      }
    },
    "season": "KCC2026",
    "sort_by": "overall_rating",
    "team_name": null,
    "total_players": 163
  }
}
