{
  "code": 200,
  "data": [
    {
      "hero_id": "503",
      "hero_name": "狂铁",
      "last_updated": "2026-04-03 13:18:30",
      "lose_matches": 82,
      "matchups": [
        {
          "enemy_hero": "夏洛特",
          "hero_id": "536",
          "losses": 26,
          "total": 52,
          "win_rate": "50.0%",
          "wins": 26
        },
        {
          "enemy_hero": "曹操",
          "hero_id": "128",
          "losses": 12,
          "total": 33,
          "win_rate": "63.6%",
          "wins": 21
        },
        {
          "enemy_hero": "影",
          "hero_id": "558",
          "losses": 9,
          "total": 23,
          "win_rate": "60.9%",
          "wins": 14
        },
        {
          "enemy_hero": "关羽",
          "hero_id": "140",
          "losses": 7,
          "total": 16,
          "win_rate": "56.2%",
          "wins": 9
        },
        {
          "enemy_hero": "司空震",
          "hero_id": "537",
          "losses": 7,
          "total": 16,
          "win_rate": "56.2%",
          "wins": 9
        },
        {
          "enemy_hero": "马超",
          "hero_id": "518",
          "losses": 6,
          "total": 12,
          "win_rate": "50.0%",
          "wins": 6
        },
        {
          "enemy_hero": "白起",
          "hero_id": "120",
          "losses": 2,
          "total": 11,
          "win_rate": "81.8%",
          "wins": 9
        },
        {
          "enemy_hero": "吕布",
          "hero_id": "123",
          "losses": 5,
          "total": 9,
          "win_rate": "44.4%",
          "wins": 4
        },
        {
          "enemy_hero": "达摩",
          "hero_id": "134",
          "losses": 4,
          "total": 9,
          "win_rate": "55.6%",
          "wins": 5
        },
        {
          "enemy_hero": "蚩奼",
          "hero_id": "172",
          "losses": 3,
          "total": 4,
          "win_rate": "25.0%",
          "wins": 1
        },
        {
          "enemy_hero": "亚连",
          "hero_id": "514",
          "losses": 1,
          "total": 1,
          "win_rate": "0.0%",
          "wins": 0
        },
        {
          "enemy_hero": "蒙恬",
          "hero_id": "527",
          "losses": 0,
          "total": 1,
          "win_rate": "100.0%",
          "wins": 1
        },
        {
          "enemy_hero": "项羽",
          "hero_id": "135",
          "losses": 0,
          "total": 1,
          "win_rate": "100.0%",
          "wins": 1
        }
      ],
      "mvp_count": 14,
      "mvp_rate": "7.5%",
      "position": "对抗路",
      "rank": 1,
      "total_matches": 188,
      "total_matchup_heroes": 13,
      "total_players": 22,
      "win_matches": 106,
      "win_rate": "56.4%"
    },
    {
      "hero_id": "536",
      "hero_name": "夏洛特",
      "last_updated": "2026-04-03 13:18:30",
      "lose_matches": 83,
      "matchups": [
        {
          "enemy_hero": "狂铁",
          "hero_id": "503",
          "losses": 26,
          "total": 52,
          "win_rate": "50.0%",
          "wins": 26
        },
        {
          "enemy_hero": "曹操",
          "hero_id": "128",
          "losses": 20,
          "total": 36,
          "win_rate": "44.4%",
          "wins": 16
        },
        {
          "enemy_hero": "司空震",
          "hero_id": "537",
          "losses": 7,
          "total": 18,
          "win_rate": "61.1%",
          "wins": 11
        },
        {
          "enemy_hero": "马超",
          "hero_id": "518",
          "losses": 7,
          "total": 17,
          "win_rate": "58.8%",
          "wins": 10
        },
        {
          "enemy_hero": "达摩",
          "hero_id": "134",
          "losses": 5,
          "total": 9,
          "win_rate": "44.4%",
          "wins": 4
        },
        {
          "enemy_hero": "影",
          "hero_id": "558",
          "losses": 5,
          "total": 8,
          "win_rate": "37.5%",
          "wins": 3
        },
        {
          "enemy_hero": "关羽",
          "hero_id": "140",
          "losses": 4,
          "total": 7,
          "win_rate": "42.9%",
          "wins": 3
        },
        {
          "enemy_hero": "蒙恬",
          "hero_id": "527",
          "losses": 4,
          "total": 7,
          "win_rate": "42.9%",
          "wins": 3
        },
        {
          "enemy_hero": "蚩奼",
          "hero_id": "172",
          "losses": 3,
          "total": 6,
          "win_rate": "50.0%",
          "wins": 3
        },
        {
          "enemy_hero": "吕布",
          "hero_id": "123",
          "losses": 1,
          "total": 1,
          "win_rate": "0.0%",
          "wins": 0
        },
        {
          "enemy_hero": "孙策",
          "hero_id": "510",
          "losses": 1,
          "total": 1,
          "win_rate": "0.0%",
          "wins": 0
        },
        {
          "enemy_hero": "姬小满",
          "hero_id": "564",
          "losses": 0,
          "total": 1,
          "win_rate": "100.0%",
          "wins": 1
        }
      ],
      "mvp_count": 17,
      "mvp_rate": "10.4%",
      "position": "对抗路",
      "rank": 2,
      "total_matches": 163,
      "total_matchup_heroes": 12,
      "total_players": 22,
      "win_matches": 80,
      "win_rate": "49.1%"
    },
    {
      "hero_id": "128",
      "hero_name": "曹操",
      "last_updated": "2026-04-03 13:18:30",
      "lose_matches": 70,
      "matchups": [
        {
          "enemy_hero": "夏洛特",
          "hero_id": "536",
          "losses": 16,
          "total": 36,
          "win_rate": "55.6%",
          "wins": 20
        },
        {
          "enemy_hero": "狂铁",
          "hero_id": "503",
          "losses": 21,
          "total": 33,
          "win_rate": "36.4%",
          "wins": 12
        },
        {
          "enemy_hero": "司空震",
          "hero_id": "537",
          "losses": 8,
          "total": 21,
          "win_rate": "61.9%",
          "wins": 13
        },
        {
          "enemy_hero": "马超",
          "hero_id": "518",
          "losses": 4,
          "total": 12,
          "win_rate": "66.7%",
          "wins": 8
        },
        {
          "enemy_hero": "关羽",
          "hero_id": "140",
          "losses": 5,
          "total": 7,
          "win_rate": "28.6%",
          "wins": 2
        },
        {
          "enemy_hero": "蒙恬",
          "hero_id": "527",
          "losses": 5,
          "total": 7,
          "win_rate": "28.6%",
          "wins": 2
        },
        {
          "enemy_hero": "白起",
          "hero_id": "120",
          "losses": 3,
          "total": 5,
          "win_rate": "40.0%",
          "wins": 2
        },
        {
          "enemy_hero": "蚩奼",
          "hero_id": "172",
          "losses": 2,
          "total": 5,
          "win_rate": "60.0%",
          "wins": 3
        },
        {
          "enemy_hero": "老夫子",
          "hero_id": "139",
          "losses": 3,
          "total": 4,
          "win_rate": "25.0%",
          "wins": 1
        },
        {
          "enemy_hero": "影",
          "hero_id": "558",
          "losses": 1,
          "total": 3,
          "win_rate": "66.7%",
          "wins": 2
        },
        {
          "enemy_hero": "达摩",
          "hero_id": "134",
          "losses": 2,
          "total": 3,
          "win_rate": "33.3%",
          "wins": 1
        },
        {
          "enemy_hero": "孙策",
          "hero_id": "510",
          "losses": 0,
          "total": 1,
          "win_rate": "100.0%",
          "wins": 1
        }
      ],
      "mvp_count": 15,
      "mvp_rate": "10.9%",
      "position": "对抗路",
      "rank": 3,
      "total_matches": 137,
      "total_matchup_heroes": 12,
      "total_players": 20,
      "win_matches": 67,
      "win_rate": "48.9%"
    },
    {
      "hero_id": "537",
      "hero_name": "司空震",
      "last_updated": "2026-04-03 13:18:30",
      "lose_matches": 67,
      "matchups": [
        {
          "enemy_hero": "曹操",
          "hero_id": "128",
          "losses": 13,
          "total": 21,
          "win_rate": "38.1%",
          "wins": 8
        },
        {
          "enemy_hero": "夏洛特",
          "hero_id": "536",
          "losses": 11,
          "total": 18,
          "win_rate": "38.9%",
          "wins": 7
        },
        {
          "enemy_hero": "狂铁",
          "hero_id": "503",
          "losses": 9,
          "total": 16,
          "win_rate": "43.8%",
          "wins": 7
        },
        {
          "enemy_hero": "白起",
          "hero_id": "120",
          "losses": 5,
          "total": 9,
          "win_rate": "44.4%",
          "wins": 4
        },
        {
          "enemy_hero": "老夫子",
          "hero_id": "139",
          "losses": 6,
          "total": 9,
          "win_rate": "33.3%",
          "wins": 3
        },
        {
          "enemy_hero": "关羽",
          "hero_id": "140",
          "losses": 3,
          "total": 8,
          "win_rate": "62.5%",
          "wins": 5
        },
        {
          "enemy_hero": "马超",
          "hero_id": "518",
          "losses": 4,
          "total": 8,
          "win_rate": "50.0%",
          "wins": 4
        },
        {
          "enemy_hero": "影",
          "hero_id": "558",
          "losses": 5,
          "total": 7,
          "win_rate": "28.6%",
          "wins": 2
        },
        {
          "enemy_hero": "蒙恬",
          "hero_id": "527",
          "losses": 3,
          "total": 6,
          "win_rate": "50.0%",
          "wins": 3
        },
        {
          "enemy_hero": "达摩",
          "hero_id": "134",
          "losses": 2,
          "total": 5,
          "win_rate": "60.0%",
          "wins": 3
        },
        {
          "enemy_hero": "蚩奼",
          "hero_id": "172",
          "losses": 2,
          "total": 4,
          "win_rate": "50.0%",
          "wins": 2
        },
        {
          "enemy_hero": "姬小满",
          "hero_id": "564",
          "losses": 1,
          "total": 2,
          "win_rate": "50.0%",
          "wins": 1
        },
        {
          "enemy_hero": "元歌",
          "hero_id": "125",
          "losses": 1,
          "total": 1,
          "win_rate": "0.0%",
          "wins": 0
        },
        {
          "enemy_hero": "吕布",
          "hero_id": "123",
          "losses": 1,
          "total": 1,
          "win_rate": "0.0%",
          "wins": 0
        },
        {
          "enemy_hero": "芈月",
          "hero_id": "121",
          "losses": 1,
          "total": 1,
          "win_rate": "0.0%",
          "wins": 0
        }
      ],
      "mvp_count": 9,
      "mvp_rate": "7.8%",
      "position": "对抗路",
      "rank": 4,
      "total_matches": 116,
      "total_matchup_heroes": 15,
      "total_players": 19,
      "win_matches": 49,
      "win_rate": "42.2%"
    },
    {
      "hero_id": "140",
      "hero_name": "关羽",
      "last_updated": "2026-04-03 13:18:31",
      "lose_matches": 46,
      "matchups": [
        {
          "enemy_hero": "马超",
          "hero_id": "518",
          "losses": 8,
          "total": 17,
          "win_rate": "52.9%",
          "wins": 9
        },
        {
          "enemy_hero": "狂铁",
          "hero_id": "503",
          "losses": 9,
          "total": 16,
          "win_rate": "43.8%",
          "wins": 7
        },
        {
          "enemy_hero": "达摩",
          "hero_id": "134",
          "losses": 5,
          "total": 12,
          "win_rate": "58.3%",
          "wins": 7
        },
        {
          "enemy_hero": "司空震",
          "hero_id": "537",
          "losses": 5,
          "total": 8,
          "win_rate": "37.5%",
          "wins": 3
        },
        {
          "enemy_hero": "姬小满",
          "hero_id": "564",
          "losses": 6,
          "total": 8,
          "win_rate": "25.0%",
          "wins": 2
        },
        {
          "enemy_hero": "曹操",
          "hero_id": "128",
          "losses": 2,
          "total": 7,
          "win_rate": "71.4%",
          "wins": 5
        },
        {
          "enemy_hero": "夏洛特",
          "hero_id": "536",
          "losses": 3,
          "total": 7,
          "win_rate": "57.1%",
          "wins": 4
        },
        {
          "enemy_hero": "影",
          "hero_id": "558",
          "losses": 4,
          "total": 6,
          "win_rate": "33.3%",
          "wins": 2
        },
        {
          "enemy_hero": "蒙恬",
          "hero_id": "527",
          "losses": 2,
          "total": 5,
          "win_rate": "60.0%",
          "wins": 3
        },
        {
          "enemy_hero": "白起",
          "hero_id": "120",
          "losses": 1,
          "total": 4,
          "win_rate": "75.0%",
          "wins": 3
        },
        {
          "enemy_hero": "项羽",
          "hero_id": "135",
          "losses": 1,
          "total": 4,
          "win_rate": "75.0%",
          "wins": 3
        },
        {
          "enemy_hero": "蚩奼",
          "hero_id": "172",
          "losses": 0,
          "total": 3,
          "win_rate": "100.0%",
          "wins": 3
        },
        {
          "enemy_hero": "老夫子",
          "hero_id": "139",
          "losses": 0,
          "total": 2,
          "win_rate": "100.0%",
          "wins": 2
        }
      ],
      "mvp_count": 17,
      "mvp_rate": "17.2%",
      "position": "对抗路",
      "rank": 5,
      "total_matches": 99,
      "total_matchup_heroes": 13,
      "total_players": 19,
      "win_matches": 53,
      "win_rate": "53.5%"
    },
    {
      "hero_id": "518",
      "hero_name": "马超",
      "last_updated": "2026-04-03 13:18:30",
      "lose_matches": 53,
      "matchups": [
        {
          "enemy_hero": "关羽",
          "hero_id": "140",
          "losses": 9,
          "total": 17,
          "win_rate": "47.1%",
          "wins": 8
        },
        {
          "enemy_hero": "夏洛特",
          "hero_id": "536",
          "losses": 10,
          "total": 17,
          "win_rate": "41.2%",
          "wins": 7
        },
        {
          "enemy_hero": "曹操",
          "hero_id": "128",
          "losses": 8,
          "total": 12,
          "win_rate": "33.3%",
          "wins": 4
        },
        {
          "enemy_hero": "狂铁",
          "hero_id": "503",
          "losses": 6,
          "total": 12,
          "win_rate": "50.0%",
          "wins": 6
        },
        {
          "enemy_hero": "司空震",
          "hero_id": "537",
          "losses": 4,
          "total": 8,
          "win_rate": "50.0%",
          "wins": 4
        },
        {
          "enemy_hero": "蒙恬",
          "hero_id": "527",
          "losses": 3,
          "total": 4,
          "win_rate": "25.0%",
          "wins": 1
        },
        {
          "enemy_hero": "元歌",
          "hero_id": "125",
          "losses": 1,
          "total": 3,
          "win_rate": "66.7%",
          "wins": 2
        },
        {
          "enemy_hero": "蚩奼",
          "hero_id": "172",
          "losses": 3,
          "total": 3,
          "win_rate": "0.0%",
          "wins": 0
        },
        {
          "enemy_hero": "达摩",
          "hero_id": "134",
          "losses": 3,
          "total": 3,
          "win_rate": "0.0%",
          "wins": 0
        },
        {
          "enemy_hero": "老夫子",
          "hero_id": "139",
          "losses": 1,
          "total": 3,
          "win_rate": "66.7%",
          "wins": 2
        },
        {
          "enemy_hero": "影",
          "hero_id": "558",
          "losses": 0,
          "total": 2,
          "win_rate": "100.0%",
          "wins": 2
        },
        {
          "enemy_hero": "孙策",
          "hero_id": "510",
          "losses": 2,
          "total": 2,
          "win_rate": "0.0%",
          "wins": 0
        },
        {
          "enemy_hero": "白起",
          "hero_id": "120",
          "losses": 2,
          "total": 2,
          "win_rate": "0.0%",
          "wins": 0
        },
        {
          "enemy_hero": "姬小满",
          "hero_id": "564",
          "losses": 1,
          "total": 2,
          "win_rate": "50.0%",
          "wins": 1
        }
      ],
      "mvp_count": 13,
      "mvp_rate": "14.4%",
      "position": "对抗路",
      "rank": 6,
      "total_matches": 90,
      "total_matchup_heroes": 14,
      "total_players": 19,
      "win_matches": 37,
      "win_rate": "41.1%"
    },
    {
      "hero_id": "558",
      "hero_name": "影",
      "last_updated": "2026-04-03 13:18:30",
      "lose_matches": 36,
      "matchups": [
        {
          "enemy_hero": "狂铁",
          "hero_id": "503",
          "losses": 14,
          "total": 23,
          "win_rate": "39.1%",
          "wins": 9
        },
        {
          "enemy_hero": "夏洛特",
          "hero_id": "536",
          "losses": 3,
          "total": 8,
          "win_rate": "62.5%",
          "wins": 5
        },
        {
          "enemy_hero": "蒙恬",
          "hero_id": "527",
          "losses": 5,
          "total": 7,
          "win_rate": "28.6%",
          "wins": 2
        },
        {
          "enemy_hero": "司空震",
          "hero_id": "537",
          "losses": 2,
          "total": 7,
          "win_rate": "71.4%",
          "wins": 5
        },
        {
          "enemy_hero": "关羽",
          "hero_id": "140",
          "losses": 2,
          "total": 6,
          "win_rate": "66.7%",
          "wins": 4
        },
        {
          "enemy_hero": "蚩奼",
          "hero_id": "172",
          "losses": 1,
          "total": 4,
          "win_rate": "75.0%",
          "wins": 3
        },
        {
          "enemy_hero": "曹操",
          "hero_id": "128",
          "losses": 2,
          "total": 3,
          "win_rate": "33.3%",
          "wins": 1
        },
        {
          "enemy_hero": "白起",
          "hero_id": "120",
          "losses": 3,
          "total": 3,
          "win_rate": "0.0%",
          "wins": 0
        },
        {
          "enemy_hero": "马超",
          "hero_id": "518",
          "losses": 2,
          "total": 2,
          "win_rate": "0.0%",
          "wins": 0
        },
        {
          "enemy_hero": "吕布",
          "hero_id": "123",
          "losses": 1,
          "total": 1,
          "win_rate": "0.0%",
          "wins": 0
        },
        {
          "enemy_hero": "梦奇",
          "hero_id": "198",
          "losses": 0,
          "total": 1,
          "win_rate": "100.0%",
          "wins": 1
        },
        {
          "enemy_hero": "达摩",
          "hero_id": "134",
          "losses": 0,
          "total": 1,
          "win_rate": "100.0%",
          "wins": 1
        },
        {
          "enemy_hero": "老夫子",
          "hero_id": "139",
          "losses": 1,
          "total": 1,
          "win_rate": "0.0%",
          "wins": 0
        }
      ],
      "mvp_count": 6,
      "mvp_rate": "9.0%",
      "position": "对抗路",
      "rank": 7,
      "total_matches": 67,
      "total_matchup_heroes": 13,
      "total_players": 19,
      "win_matches": 31,
      "win_rate": "46.3%"
    },
    {
      "hero_id": "527",
      "hero_name": "蒙恬",
      "last_updated": "2026-04-03 13:18:31",
      "lose_matches": 26,
      "matchups": [
        {
          "enemy_hero": "影",
          "hero_id": "558",
          "losses": 2,
          "total": 7,
          "win_rate": "71.4%",
          "wins": 5
        },
        {
          "enemy_hero": "曹操",
          "hero_id": "128",
          "losses": 2,
          "total": 7,
          "win_rate": "71.4%",
          "wins": 5
        },
        {
          "enemy_hero": "夏洛特",
          "hero_id": "536",
          "losses": 3,
          "total": 7,
          "win_rate": "57.1%",
          "wins": 4
        },
        {
          "enemy_hero": "司空震",
          "hero_id": "537",
          "losses": 3,
          "total": 6,
          "win_rate": "50.0%",
          "wins": 3
        },
        {
          "enemy_hero": "关羽",
          "hero_id": "140",
          "losses": 3,
          "total": 5,
          "win_rate": "40.0%",
          "wins": 2
        },
        {
          "enemy_hero": "吕布",
          "hero_id": "123",
          "losses": 3,
          "total": 4,
          "win_rate": "25.0%",
          "wins": 1
        },
        {
          "enemy_hero": "蚩奼",
          "hero_id": "172",
          "losses": 2,
          "total": 4,
          "win_rate": "50.0%",
          "wins": 2
        },
        {
          "enemy_hero": "马超",
          "hero_id": "518",
          "losses": 1,
          "total": 4,
          "win_rate": "75.0%",
          "wins": 3
        },
        {
          "enemy_hero": "白起",
          "hero_id": "120",
          "losses": 2,
          "total": 3,
          "win_rate": "33.3%",
          "wins": 1
        },
        {
          "enemy_hero": "达摩",
          "hero_id": "134",
          "losses": 1,
          "total": 3,
          "win_rate": "66.7%",
          "wins": 2
        },
        {
          "enemy_hero": "猪八戒",
          "hero_id": "511",
          "losses": 2,
          "total": 2,
          "win_rate": "0.0%",
          "wins": 0
        },
        {
          "enemy_hero": "狂铁",
          "hero_id": "503",
          "losses": 1,
          "total": 1,
          "win_rate": "0.0%",
          "wins": 0
        },
        {
          "enemy_hero": "老夫子",
          "hero_id": "139",
          "losses": 1,
          "total": 1,
          "win_rate": "0.0%",
          "wins": 0
        }
      ],
      "mvp_count": 2,
      "mvp_rate": "3.7%",
      "position": "对抗路",
      "rank": 8,
      "total_matches": 54,
      "total_matchup_heroes": 13,
      "total_players": 17,
      "win_matches": 28,
      "win_rate": "51.9%"
    },
    {
      "hero_id": "134",
      "hero_name": "达摩",
      "last_updated": "2026-04-03 13:18:30",
      "lose_matches": 25,
      "matchups": [
        {
          "enemy_hero": "关羽",
          "hero_id": "140",
          "losses": 7,
          "total": 12,
          "win_rate": "41.7%",
          "wins": 5
        },
        {
          "enemy_hero": "狂铁",
          "hero_id": "503",
          "losses": 5,
          "total": 9,
          "win_rate": "44.4%",
          "wins": 4
        },
        {
          "enemy_hero": "夏洛特",
          "hero_id": "536",
          "losses": 4,
          "total": 9,
          "win_rate": "55.6%",
          "wins": 5
        },
        {
          "enemy_hero": "司空震",
          "hero_id": "537",
          "losses": 3,
          "total": 5,
          "win_rate": "40.0%",
          "wins": 2
        },
        {
          "enemy_hero": "曹操",
          "hero_id": "128",
          "losses": 1,
          "total": 3,
          "win_rate": "66.7%",
          "wins": 2
        },
        {
          "enemy_hero": "蒙恬",
          "hero_id": "527",
          "losses": 2,
          "total": 3,
          "win_rate": "33.3%",
          "wins": 1
        },
        {
          "enemy_hero": "马超",
          "hero_id": "518",
          "losses": 0,
          "total": 3,
          "win_rate": "100.0%",
          "wins": 3
        },
        {
          "enemy_hero": "刘邦",
          "hero_id": "149",
          "losses": 1,
          "total": 2,
          "win_rate": "50.0%",
          "wins": 1
        },
        {
          "enemy_hero": "白起",
          "hero_id": "120",
          "losses": 1,
          "total": 2,
          "win_rate": "50.0%",
          "wins": 1
        },
        {
          "enemy_hero": "影",
          "hero_id": "558",
          "losses": 1,
          "total": 1,
          "win_rate": "0.0%",
          "wins": 0
        },
        {
          "enemy_hero": "吕布",
          "hero_id": "123",
          "losses": 0,
          "total": 1,
          "win_rate": "100.0%",
          "wins": 1
        }
      ],
      "mvp_count": 6,
      "mvp_rate": "12.0%",
      "position": "对抗路",
      "rank": 9,
      "total_matches": 50,
      "total_matchup_heroes": 11,
      "total_players": 15,
      "win_matches": 25,
      "win_rate": "50.0%"
    },
    {
      "hero_id": "120",
      "hero_name": "白起",
      "last_updated": "2026-04-03 13:18:32",
      "lose_matches": 20,
      "matchups": [
        {
          "enemy_hero": "狂铁",
          "hero_id": "503",
          "losses": 9,
          "total": 11,
          "win_rate": "18.2%",
          "wins": 2
        },
        {
          "enemy_hero": "司空震",
          "hero_id": "537",
          "losses": 4,
          "total": 9,
          "win_rate": "55.6%",
          "wins": 5
        },
        {
          "enemy_hero": "曹操",
          "hero_id": "128",
          "losses": 2,
          "total": 5,
          "win_rate": "60.0%",
          "wins": 3
        },
        {
          "enemy_hero": "关羽",
          "hero_id": "140",
          "losses": 3,
          "total": 4,
          "win_rate": "25.0%",
          "wins": 1
        },
        {
          "enemy_hero": "影",
          "hero_id": "558",
          "losses": 0,
          "total": 3,
          "win_rate": "100.0%",
          "wins": 3
        },
        {
          "enemy_hero": "蒙恬",
          "hero_id": "527",
          "losses": 1,
          "total": 3,
          "win_rate": "66.7%",
          "wins": 2
        },
        {
          "enemy_hero": "达摩",
          "hero_id": "134",
          "losses": 1,
          "total": 2,
          "win_rate": "50.0%",
          "wins": 1
        },
        {
          "enemy_hero": "马超",
          "hero_id": "518",
          "losses": 0,
          "total": 2,
          "win_rate": "100.0%",
          "wins": 2
        },
        {
          "enemy_hero": "庄周",
          "hero_id": "113",
          "losses": 0,
          "total": 1,
          "win_rate": "100.0%",
          "wins": 1
        },
        {
          "enemy_hero": "芈月",
          "hero_id": "121",
          "losses": 0,
          "total": 1,
          "win_rate": "100.0%",
          "wins": 1
        }
      ],
      "mvp_count": 13,
      "mvp_rate": "31.7%",
      "position": "对抗路",
      "rank": 10,
      "total_matches": 41,
      "total_matchup_heroes": 10,
      "total_players": 14,
      "win_matches": 21,
      "win_rate": "51.2%"
    },
    {
      "hero_id": "172",
      "hero_name": "蚩奼",
      "last_updated": "2026-04-03 13:18:31",
      "lose_matches": 18,
      "matchups": [
        {
          "enemy_hero": "夏洛特",
          "hero_id": "536",
          "losses": 3,
          "total": 6,
          "win_rate": "50.0%",
          "wins": 3
        },
        {
          "enemy_hero": "曹操",
          "hero_id": "128",
          "losses": 3,
          "total": 5,
          "win_rate": "40.0%",
          "wins": 2
        },
        {
          "enemy_hero": "影",
          "hero_id": "558",
          "losses": 3,
          "total": 4,
          "win_rate": "25.0%",
          "wins": 1
        },
        {
          "enemy_hero": "狂铁",
          "hero_id": "503",
          "losses": 1,
          "total": 4,
          "win_rate": "75.0%",
          "wins": 3
        },
        {
          "enemy_hero": "蒙恬",
          "hero_id": "527",
          "losses": 2,
          "total": 4,
          "win_rate": "50.0%",
          "wins": 2
        },
        {
          "enemy_hero": "司空震",
          "hero_id": "537",
          "losses": 2,
          "total": 4,
          "win_rate": "50.0%",
          "wins": 2
        },
        {
          "enemy_hero": "关羽",
          "hero_id": "140",
          "losses": 3,
          "total": 3,
          "win_rate": "0.0%",
          "wins": 0
        },
        {
          "enemy_hero": "马超",
          "hero_id": "518",
          "losses": 0,
          "total": 3,
          "win_rate": "100.0%",
          "wins": 3
        },
        {
          "enemy_hero": "老夫子",
          "hero_id": "139",
          "losses": 1,
          "total": 1,
          "win_rate": "0.0%",
          "wins": 0
        }
      ],
      "mvp_count": 6,
      "mvp_rate": "17.6%",
      "position": "对抗路",
      "rank": 11,
      "total_matches": 34,
      "total_matchup_heroes": 9,
      "total_players": 15,
      "win_matches": 16,
      "win_rate": "47.1%"
    },
    {
      "hero_id": "139",
      "hero_name": "老夫子",
      "last_updated": "2026-04-03 13:18:31",
      "lose_matches": 8,
      "matchups": [
        {
          "enemy_hero": "司空震",
          "hero_id": "537",
          "losses": 3,
          "total": 9,
          "win_rate": "66.7%",
          "wins": 6
        },
        {
          "enemy_hero": "曹操",
          "hero_id": "128",
          "losses": 1,
          "total": 4,
          "win_rate": "75.0%",
          "wins": 3
        },
        {
          "enemy_hero": "马超",
          "hero_id": "518",
          "losses": 2,
          "total": 3,
          "win_rate": "33.3%",
          "wins": 1
        },
        {
          "enemy_hero": "关羽",
          "hero_id": "140",
          "losses": 2,
          "total": 2,
          "win_rate": "0.0%",
          "wins": 0
        },
        {
          "enemy_hero": "影",
          "hero_id": "558",
          "losses": 0,
          "total": 1,
          "win_rate": "100.0%",
          "wins": 1
        },
        {
          "enemy_hero": "蒙恬",
          "hero_id": "527",
          "losses": 0,
          "total": 1,
          "win_rate": "100.0%",
          "wins": 1
        },
        {
          "enemy_hero": "蚩奼",
          "hero_id": "172",
          "losses": 0,
          "total": 1,
          "win_rate": "100.0%",
          "wins": 1
        },
        {
          "enemy_hero": "项羽",
          "hero_id": "135",
          "losses": 0,
          "total": 1,
          "win_rate": "100.0%",
          "wins": 1
        }
      ],
      "mvp_count": 10,
      "mvp_rate": "45.5%",
      "position": "对抗路",
      "rank": 12,
      "total_matches": 22,
      "total_matchup_heroes": 8,
      "total_players": 11,
      "win_matches": 14,
      "win_rate": "63.6%"
    },
    {
      "hero_id": "123",
      "hero_name": "吕布",
      "last_updated": "2026-04-03 13:18:31",
      "lose_matches": 6,
      "matchups": [
        {
          "enemy_hero": "狂铁",
          "hero_id": "503",
          "losses": 4,
          "total": 9,
          "win_rate": "55.6%",
          "wins": 5
        },
        {
          "enemy_hero": "蒙恬",
          "hero_id": "527",
          "losses": 1,
          "total": 4,
          "win_rate": "75.0%",
          "wins": 3
        },
        {
          "enemy_hero": "影",
          "hero_id": "558",
          "losses": 0,
          "total": 1,
          "win_rate": "100.0%",
          "wins": 1
        },
        {
          "enemy_hero": "达摩",
          "hero_id": "134",
          "losses": 1,
          "total": 1,
          "win_rate": "0.0%",
          "wins": 0
        },
        {
          "enemy_hero": "司空震",
          "hero_id": "537",
          "losses": 0,
          "total": 1,
          "win_rate": "100.0%",
          "wins": 1
        },
        {
          "enemy_hero": "夏洛特",
          "hero_id": "536",
          "losses": 0,
          "total": 1,
          "win_rate": "100.0%",
          "wins": 1
        }
      ],
      "mvp_count": 3,
      "mvp_rate": "17.6%",
      "position": "对抗路",
      "rank": 13,
      "total_matches": 17,
      "total_matchup_heroes": 6,
      "total_players": 9,
      "win_matches": 11,
      "win_rate": "64.7%"
    },
    {
      "hero_id": "564",
      "hero_name": "姬小满",
      "last_updated": "2026-04-03 13:18:31",
      "lose_matches": 5,
      "matchups": [
        {
          "enemy_hero": "关羽",
          "hero_id": "140",
          "losses": 2,
          "total": 8,
          "win_rate": "75.0%",
          "wins": 6
        },
        {
          "enemy_hero": "马超",
          "hero_id": "518",
          "losses": 1,
          "total": 2,
          "win_rate": "50.0%",
          "wins": 1
        },
        {
          "enemy_hero": "司空震",
          "hero_id": "537",
          "losses": 1,
          "total": 2,
          "win_rate": "50.0%",
          "wins": 1
        },
        {
          "enemy_hero": "夏洛特",
          "hero_id": "536",
          "losses": 1,
          "total": 1,
          "win_rate": "0.0%",
          "wins": 0
        }
      ],
      "mvp_count": 1,
      "mvp_rate": "7.7%",
      "position": "对抗路",
      "rank": 14,
      "total_matches": 13,
      "total_matchup_heroes": 4,
      "total_players": 6,
      "win_matches": 8,
      "win_rate": "61.5%"
    },
    {
      "hero_id": "135",
      "hero_name": "项羽",
      "last_updated": "2026-04-03 13:18:32",
      "lose_matches": 5,
      "matchups": [
        {
          "enemy_hero": "关羽",
          "hero_id": "140",
          "losses": 3,
          "total": 4,
          "win_rate": "25.0%",
          "wins": 1
        },
        {
          "enemy_hero": "狂铁",
          "hero_id": "503",
          "losses": 1,
          "total": 1,
          "win_rate": "0.0%",
          "wins": 0
        },
        {
          "enemy_hero": "老夫子",
          "hero_id": "139",
          "losses": 1,
          "total": 1,
          "win_rate": "0.0%",
          "wins": 0
        }
      ],
      "mvp_count": 0,
      "mvp_rate": "0.0%",
      "position": "对抗路",
      "rank": 15,
      "total_matches": 6,
      "total_matchup_heroes": 3,
      "total_players": 4,
      "win_matches": 1,
      "win_rate": "16.7%"
    },
    {
      "hero_id": "510",
      "hero_name": "孙策",
      "last_updated": "2026-04-03 13:18:32",
      "lose_matches": 1,
      "matchups": [
        {
          "enemy_hero": "马超",
          "hero_id": "518",
          "losses": 0,
          "total": 2,
          "win_rate": "100.0%",
          "wins": 2
        },
        {
          "enemy_hero": "曹操",
          "hero_id": "128",
          "losses": 1,
          "total": 1,
          "win_rate": "0.0%",
          "wins": 0
        },
        {
          "enemy_hero": "夏洛特",
          "hero_id": "536",
          "losses": 0,
          "total": 1,
          "win_rate": "100.0%",
          "wins": 1
        }
      ],
      "mvp_count": 2,
      "mvp_rate": "50.0%",
      "position": "对抗路",
      "rank": 16,
      "total_matches": 4,
      "total_matchup_heroes": 3,
      "total_players": 2,
      "win_matches": 3,
      "win_rate": "75.0%"
    },
    {
      "hero_id": "125",
      "hero_name": "元歌",
      "last_updated": "2026-04-03 13:18:32",
      "lose_matches": 2,
      "matchups": [
        {
          "enemy_hero": "马超",
          "hero_id": "518",
          "losses": 2,
          "total": 3,
          "win_rate": "33.3%",
          "wins": 1
        },
        {
          "enemy_hero": "司空震",
          "hero_id": "537",
          "losses": 0,
          "total": 1,
          "win_rate": "100.0%",
          "wins": 1
        }
      ],
      "mvp_count": 0,
      "mvp_rate": "0.0%",
      "position": "对抗路",
      "rank": 17,
      "total_matches": 4,
      "total_matchup_heroes": 2,
      "total_players": 3,
      "win_matches": 2,
      "win_rate": "50.0%"
    },
    {
      "hero_id": "511",
      "hero_name": "猪八戒",
      "last_updated": "2026-04-03 13:18:32",
      "lose_matches": 0,
      "matchups": [
        {
          "enemy_hero": "蒙恬",
          "hero_id": "527",
          "losses": 0,
          "total": 2,
          "win_rate": "100.0%",
          "wins": 2
        }
      ],
      "mvp_count": 0,
      "mvp_rate": "0.0%",
      "position": "对抗路",
      "rank": 18,
      "total_matches": 2,
      "total_matchup_heroes": 1,
      "total_players": 2,
      "win_matches": 2,
      "win_rate": "100.0%"
    },
    {
      "hero_id": "121",
      "hero_name": "芈月",
      "last_updated": "2026-04-03 13:18:32",
      "lose_matches": 1,
      "matchups": [
        {
          "enemy_hero": "白起",
          "hero_id": "120",
          "losses": 1,
          "total": 1,
          "win_rate": "0.0%",
          "wins": 0
        },
        {
          "enemy_hero": "司空震",
          "hero_id": "537",
          "losses": 0,
          "total": 1,
          "win_rate": "100.0%",
          "wins": 1
        }
      ],
      "mvp_count": 1,
      "mvp_rate": "50.0%",
      "position": "对抗路",
      "rank": 19,
      "total_matches": 2,
      "total_matchup_heroes": 2,
      "total_players": 2,
      "win_matches": 1,
      "win_rate": "50.0%"
    },
    {
      "hero_id": "149",
      "hero_name": "刘邦",
      "last_updated": "2026-04-03 13:18:32",
      "lose_matches": 1,
      "matchups": [
        {
          "enemy_hero": "达摩",
          "hero_id": "134",
          "losses": 1,
          "total": 2,
          "win_rate": "50.0%",
          "wins": 1
        }
      ],
      "mvp_count": 1,
      "mvp_rate": "50.0%",
      "position": "对抗路",
      "rank": 20,
      "total_matches": 2,
      "total_matchup_heroes": 1,
      "total_players": 1,
      "win_matches": 1,
      "win_rate": "50.0%"
    },
    {
      "hero_id": "198",
      "hero_name": "梦奇",
      "last_updated": "2026-04-03 13:18:31",
      "lose_matches": 1,
      "matchups": [
        {
          "enemy_hero": "影",
          "hero_id": "558",
          "losses": 1,
          "total": 1,
          "win_rate": "0.0%",
          "wins": 0
        }
      ],
      "mvp_count": 0,
      "mvp_rate": "0.0%",
      "position": "对抗路",
      "rank": 21,
      "total_matches": 1,
      "total_matchup_heroes": 1,
      "total_players": 1,
      "win_matches": 0,
      "win_rate": "0.0%"
    },
    {
      "hero_id": "514",
      "hero_name": "亚连",
      "last_updated": "2026-04-03 13:18:32",
      "lose_matches": 0,
      "matchups": [
        {
          "enemy_hero": "狂铁",
          "hero_id": "503",
          "losses": 0,
          "total": 1,
          "win_rate": "100.0%",
          "wins": 1
        }
      ],
      "mvp_count": 1,
      "mvp_rate": "100.0%",
      "position": "对抗路",
      "rank": 22,
      "total_matches": 1,
      "total_matchup_heroes": 1,
      "total_players": 1,
      "win_matches": 1,
      "win_rate": "100.0%"
    },
    {
      "hero_id": "113",
      "hero_name": "庄周",
      "last_updated": "2026-04-03 13:18:32",
      "lose_matches": 1,
      "matchups": [
        {
          "enemy_hero": "白起",
          "hero_id": "120",
          "losses": 1,
          "total": 1,
          "win_rate": "0.0%",
          "wins": 0
        }
      ],
      "mvp_count": 0,
      "mvp_rate": "0.0%",
      "position": "对抗路",
      "rank": 23,
      "total_matches": 1,
      "total_matchup_heroes": 1,
      "total_players": 1,
      "win_matches": 0,
      "win_rate": "0.0%"
    }
  ],
  "hero_name": null,
  "min_matches": 1,
  "position": "对抗路",
  "season": "KPL2026S1",
  "sort_by": "total_matches",
  "total_heroes": 23
}